pyloess/__init__.py
pyloess/loess.py
pyloess-0.1.0.dist-info/LICENSE.txt
pyloess-0.1.0.dist-info/METADATA
pyloess-0.1.0.dist-info/WHEEL
pyloess-0.1.0.dist-info/top_level.txt
pyloess-0.1.0.dist-info/RECORD
