Metadata-Version: 2.1
Name: pyloess
Version: 0.1.0
Summary: A fast implementation of the LOESS algorithm in Python
Author-email: Naitian Zhou <naitian@berkeley.edu>
Project-URL: Homepage, https://github.com/naitian/pyloess
Project-URL: Issues, https://github.com/naitian/pyloess/issues
Classifier: Programming Language :: Python :: 3
Classifier: License :: OSI Approved :: MIT License
Classifier: Operating System :: OS Independent
Requires-Python: >=3.8
License-File: LICENSE.txt
